Metadata-Version: 2.1
Name: Calculate-ed
Version: 0.1
Summary: cal
Home-page: UNKNOWN
Author: ankit
License: UNKNOWN
Platform: UNKNOWN
